contactssync/__init__.py
contactssync/addresses.py
contactssync/api.py
contactssync/base.py
contactssync/connect.py
contactssync/nicknames.py
contactssync/phones.py
contactssync/search.py
contactssync/types.py
contactssync/utils.py
contactssync/vars.py
contactssync/__data__/names.csv
contactssync/subtypes/__init__.py
contactssync/subtypes/airtable.py
contactssync/subtypes/api.py
contactssync/subtypes/contactsplus.py
contactssync/subtypes/google.py
contactssync-0.1.28.dist-info/LICENSE.txt
contactssync-0.1.28.dist-info/METADATA
contactssync-0.1.28.dist-info/WHEEL
contactssync-0.1.28.dist-info/top_level.txt
contactssync-0.1.28.dist-info/RECORD
