Metadata-Version: 2.1
Name: contactssync
Version: 0.1.28
Summary: Sync contacts
Home-page: https://github.com/nadime/contactssync
Author: nadime
Author-email: scottpriceasher@gmail.com
License: MIT
Platform: any
Classifier: Development Status :: 4 - Beta
Classifier: Intended Audience :: Developers
Classifier: License :: OSI Approved :: MIT License
Classifier: Operating System :: OS Independent
Classifier: Programming Language :: Python
Classifier: Programming Language :: Python :: 3
Classifier: Programming Language :: Python :: 3 :: Only
Classifier: Programming Language :: Python :: 3.7
Classifier: Programming Language :: Python :: 3.8
Classifier: Programming Language :: Python :: 3.9
Classifier: Programming Language :: Python :: 3.10
Classifier: Programming Language :: Python :: Implementation :: CPython
Classifier: Topic :: Software Development :: Libraries :: Python Modules
Classifier: Topic :: Software Development :: Localization
Requires-Python: >=3.7
License-File: LICENSE.txt
Requires-Dist: airtable-python-wrapper
Requires-Dist: attrs
Requires-Dist: google-auth-oauthlib
Requires-Dist: google-api-python-client
Requires-Dist: google-auth-httplib2
Requires-Dist: google
Requires-Dist: jinja2
Requires-Dist: pandas
Requires-Dist: phonenumbers
